{
  "Platforms": {
    "Mac": {
      "IncludeDirectories": [],
      "PlatformSpecificDefines": [],
      "ModuleDependencies": []
    }
  },
  "IncludeDirectories": [
    "macos/macos"
  ],
  "PlatformSpecificDefines": [
    "MODIO_TARGET_PLATFORM_ID=\"MACOS\"",
    "MODIO_UNREAL_PLATFORM_PREAMBLE=\"macos/detail/ModioUEPlatformPreamble.h\"",
    "MODIO_UNREAL_PLATFORM_EPILOGUE=\"macos/detail/ModioUEPlatformEpilogue.h\"",
    "MODIO_TARGET_PLATFORM_HEADER=\"Mac\""
  ],
  "ModuleDependencies": [
  ]
}
